[
    {
        "position": [
            [
                473.0,
                86.66667175292969
            ],
            [
                1045.6500244140625,
                139.6666717529297
            ]
        ],
        "type": "a",
        "color": [
            239,
            239,
            239
        ],
        "text": "FLAT - An Ice Skating FPS",
        "on_click_jump_to": "http://flat.jbushproductions.com/index.php"
    },
    {
        "position": [
            [
                473.0,
                157.3333282470703
            ],
            [
                572.0,
                184.3333282470703
            ]
        ],
        "type": "a",
        "color": [
            239,
            239,
            239
        ],
        "text": "About FLAT",
        "on_click_jump_to": "http://flat.jbushproductions.com/index.php?page=About_FLAT"
    },
    {
        "position": [
            [
                576.0,
                157.3333282470703
            ],
            [
                672.0,
                184.3333282470703
            ]
        ],
        "type": "a",
        "color": [
            239,
            239,
            239
        ],
        "text": "Downloads",
        "on_click_jump_to": "http://flat.jbushproductions.com/index.php?page=Downloads"
    },
    {
        "position": [
            [
                676.0,
                157.3333282470703
            ],
            [
                731.0,
                184.3333282470703
            ]
        ],
        "type": "a",
        "color": [
            239,
            239,
            239
        ],
        "text": "Help",
        "on_click_jump_to": "#"
    },
    {
        "position": [
            [
                735.0,
                157.3333282470703
            ],
            [
                838.0,
                184.3333282470703
            ]
        ],
        "type": "a",
        "color": [
            239,
            239,
            239
        ],
        "text": "Screenshots",
        "on_click_jump_to": "#"
    },
    {
        "position": [
            [
                842.0,
                157.3333282470703
            ],
            [
                911.0,
                184.3333282470703
            ]
        ],
        "type": "a",
        "color": [
            239,
            239,
            239
        ],
        "text": "Videos",
        "on_click_jump_to": "http://flat.jbushproductions.com/index.php?page=Videos"
    },
    {
        "position": [
            [
                915.0,
                157.3333282470703
            ],
            [
                1036.0,
                184.3333282470703
            ]
        ],
        "type": "a",
        "color": [
            239,
            239,
            239
        ],
        "text": "T-shirts/Prints »",
        "on_click_jump_to": "https://www.redbubble.com/people/cheeseness/shop?artistUserName=Cheeseness&collections=3237431&iaCode=all-departments&sortOrder=relevant"
    },
    {
        "position": [
            [
                1040.0,
                157.3333282470703
            ],
            [
                1192.0,
                184.3333282470703
            ]
        ],
        "type": "a",
        "color": [
            239,
            239,
            239
        ],
        "text": "Source/Contribute »",
        "on_click_jump_to": "https://gitlab.com/Cheeseness/FLAT"
    },
    {
        "position": [
            [
                1196.0,
                157.3333282470703
            ],
            [
                1272.0,
                184.3333282470703
            ]
        ],
        "type": "a",
        "color": [
            239,
            239,
            239
        ],
        "text": "Itch.io »",
        "on_click_jump_to": "https://cheeseness.itch.io/flat"
    },
    {
        "position": [
            [
                1212.0,
                240.8333282470703
            ],
            [
                1311.6166687011719,
                257.8333282470703
            ]
        ],
        "type": "a",
        "color": [
            239,
            239,
            239
        ],
        "text": "Known Issues",
        "on_click_jump_to": "#known_issues.txt"
    },
    {
        "position": [
            [
                1212.0,
                264.83331298828125
            ],
            [
                1353.4166717529297,
                281.83331298828125
            ]
        ],
        "type": "a",
        "color": [
            239,
            239,
            239
        ],
        "text": "Reporting Problems",
        "on_click_jump_to": "#reporting_bugs.txt"
    },
    {
        "position": [
            [
                1212.0,
                288.83331298828125
            ],
            [
                1326.1666717529297,
                305.83331298828125
            ]
        ],
        "type": "a",
        "color": [
            239,
            239,
            239
        ],
        "text": "Troubleshooting",
        "on_click_jump_to": "#troubleshooting.txt"
    },
    {
        "position": [
            [
                1053.0,
                231.6666717529297
            ],
            [
                1165.0,
                246.6666717529297
            ]
        ],
        "type": "a",
        "color": [
            239,
            239,
            239
        ],
        "text": "» Download Source",
        "on_click_jump_to": "http://flat.jbushproductions.com/content/Help/Troubleshooting/known_issues.txt"
    },
    {
        "position": [
            [
                1085.0,
                216.6666717529297
            ],
            [
                1165.0,
                231.6666717529297
            ]
        ],
        "type": "a",
        "color": [
            239,
            239,
            239
        ],
        "text": "» Link To This",
        "on_click_jump_to": "#known_issues.txt"
    },
    {
        "position": [
            [
                727.0,
                278.566650390625
            ],
            [
                873.0,
                294.566650390625
            ]
        ],
        "type": "a",
        "color": [
            239,
            239,
            239
        ],
        "text": "FLAT GitLab repository",
        "on_click_jump_to": "https://gitlab.com/Cheeseness/FLAT/issues"
    },
    {
        "position": [
            [
                1053.0,
                502.2000122070313
            ],
            [
                1165.0,
                517.2000122070312
            ]
        ],
        "type": "a",
        "color": [
            239,
            239,
            239
        ],
        "text": "» Download Source",
        "on_click_jump_to": "http://flat.jbushproductions.com/content/Help/Troubleshooting/reporting_bugs.txt"
    },
    {
        "position": [
            [
                1085.0,
                487.2000122070313
            ],
            [
                1165.0,
                502.2000122070313
            ]
        ],
        "type": "a",
        "color": [
            239,
            239,
            239
        ],
        "text": "» Link To This",
        "on_click_jump_to": "#reporting_bugs.txt"
    },
    {
        "position": [
            [
                696.7333374023438,
                525.0999755859375
            ],
            [
                773.1999969482422,
                541.0999755859375
            ]
        ],
        "type": "a",
        "color": [
            239,
            239,
            239
        ],
        "text": "issues page",
        "on_click_jump_to": "https://gitlab.com/Cheeseness/FLAT/issues"
    },
    {
        "position": [
            [
                849.88330078125,
                673.9000244140625
            ],
            [
                937.0666351318359,
                689.9000244140625
            ]
        ],
        "type": "a",
        "color": [
            239,
            239,
            239
        ],
        "text": "email Cheese",
        "on_click_jump_to": "mailto:cheese@twolofbees.com"
    },
    {
        "position": [
            [
                1053.0,
                833.63330078125
            ],
            [
                1165.0,
                848.63330078125
            ]
        ],
        "type": "a",
        "color": [
            239,
            239,
            239
        ],
        "text": "» Download Source",
        "on_click_jump_to": "http://flat.jbushproductions.com/content/Help/Troubleshooting/troubleshooting.txt"
    },
    {
        "position": [
            [
                1085.0,
                818.63330078125
            ],
            [
                1165.0,
                833.63330078125
            ]
        ],
        "type": "a",
        "color": [
            239,
            239,
            239
        ],
        "text": "» Link To This",
        "on_click_jump_to": "#troubleshooting.txt"
    },
    {
        "position": [
            [
                490.0,
                942.933349609375
            ],
            [
                1165.0,
                982.933349609375
            ]
        ],
        "type": "a",
        "color": [
            239,
            239,
            239
        ],
        "text": "list of issues",
        "on_click_jump_to": "https://gitlab.com/Cheeseness/FLAT/issues"
    },
    {
        "position": [
            [
                859.0,
                1082.3333740234375
            ],
            [
                963.0,
                1097.3333740234375
            ]
        ],
        "type": "a",
        "color": [
            239,
            239,
            239
        ],
        "text": "FLAT Contributors",
        "on_click_jump_to": "http://gitlab.com/cheeseness/FLAT"
    },
    {
        "position": [
            [
                1043.0,
                1082.3333740234375
            ],
            [
                1103.0,
                1097.3333740234375
            ]
        ],
        "type": "a",
        "color": [
            239,
            239,
            239
        ],
        "text": "Para CMS",
        "on_click_jump_to": "http://para.jbushproductions.com/"
    },
    {
        "position": [
            [
                460.0,
                64.0
            ],
            [
                1460.0,
                1113.3333740234375
            ]
        ],
        "type": "background-image",
        "src": "http://flat.jbushproductions.com/images/background2.png"
    },
    {
        "position": [
            [
                460.0,
                64.0
            ],
            [
                1460.0,
                1113.3333740234375
            ]
        ],
        "type": "background-image",
        "src": "http://flat.jbushproductions.com/images/logo.png"
    }
]